Metadata-Version: 2.1
Name: pygcurse
Version: 1.0.1
Summary: Pygcurse (pronounced "pig curse") is a curses library emulator that runs on top of the Pygame framework.
Home-page: https://github.com/asweigart/pygcurse
Author: Al Sweigart
Author-email: al@inventwithpython.com
License: BSD
Keywords: pygame curses ncurses console text game 2D graphics
Platform: UNKNOWN
Classifier: License :: OSI Approved :: MIT License
Classifier: Programming Language :: Python
Classifier: Programming Language :: Python :: 2
Classifier: Programming Language :: Python :: 2.6
Classifier: Programming Language :: Python :: 2.7
Classifier: Programming Language :: Python :: 3
Classifier: Programming Language :: Python :: 3.1
Classifier: Programming Language :: Python :: 3.2
Classifier: Programming Language :: Python :: 3.3
Classifier: Programming Language :: Python :: 3.4
Classifier: Programming Language :: Python :: 3.5
Classifier: Programming Language :: Python :: 3.6
Classifier: Programming Language :: Python :: 3.7
Classifier: Programming Language :: Python :: 3.8
Classifier: Programming Language :: Python :: 3.9
